ton_ocr/__init__.py
ton_ocr/pipeline.py
ton_ocr/det/__init__.py
ton_ocr/det/postprocess.py
ton_ocr/det/predict_det.py
ton_ocr/det/preprocess.py
ton_ocr/models/text_detection.onnx
ton_ocr/models/text_recognition.onnx
ton_ocr/rec/__init__.py
ton_ocr/rec/predict_rec.py
ton_ocr/rec/rec_decoder.py
ton_ocr/rec/vocabs.txt
ton_ocr-0.2.3.dist-info/METADATA
ton_ocr-0.2.3.dist-info/WHEEL
ton_ocr-0.2.3.dist-info/top_level.txt
ton_ocr-0.2.3.dist-info/RECORD
